<?xml version="1.0" encoding="UTF-8"?>
<objects serializationModel="Studio.02.02.00">
	<object class="AudioFile" id="{2e41bd9d-e16f-4f03-a5cd-3c3dd6cd87d4}">
		<property name="assetPath">
			<value>match3_gummy_level1.ogg</value>
		</property>
		<property name="frequencyInKHz">
			<value>44.0999985</value>
		</property>
		<property name="channelCount">
			<value>1</value>
		</property>
		<property name="length">
			<value>2.25</value>
		</property>
		<relationship name="masterAssetFolder">
			<destination>{e7c1d070-716b-446e-8fa3-1bb48b921117}</destination>
		</relationship>
	</object>
</objects>
